spreadsheet_migrator/__init__.py
spreadsheet_migrator/urls.py
spreadsheet_migrator/views.py
spreadsheet_migrator/spreadsheet_migrator_lib/__init__.py
spreadsheet_migrator/spreadsheet_migrator_lib/parser.py
spreadsheet_migrator/spreadsheet_migrator_lib/service.py
spreadsheet_migrator/spreadsheet_migrator_lib/testy_creator.py
spreadsheet_migrator/spreadsheet_migrator_lib/testy_exception.py
spreadsheet_migrator/spreadsheet_migrator_lib/logs/__init__.py
spreadsheet_migrator/spreadsheet_migrator_lib/logs/cases_logs.py
spreadsheet_migrator/spreadsheet_migrator_lib/logs/parameters_logs.py
spreadsheet_migrator/spreadsheet_migrator_lib/logs/plans_logs.py
spreadsheet_migrator/spreadsheet_migrator_lib/logs/suites_logs.py
spreadsheet_migrator/static/excel_parser/js/index.js
spreadsheet_migrator/static/excel_parser/js/mix-manifest.json
spreadsheet_migrator/templates/spreadsheet_migrator_index.html
spreadsheet_migrator-1.0.dist-info/LICENSE
spreadsheet_migrator-1.0.dist-info/METADATA
spreadsheet_migrator-1.0.dist-info/WHEEL
spreadsheet_migrator-1.0.dist-info/top_level.txt
spreadsheet_migrator-1.0.dist-info/RECORD
