Metadata-Version: 2.1
Name: spreadsheet-migrator
Version: 1.0
Summary: Plugin to migrate your data from spreadsheets
Author: Daniel
Author-email: danielsheh02@gmail.com
License-File: LICENSE
Requires-Dist: openpyxl (==3.1.1)
